{
  "type": "modal",
  "callback_id": "plan_menu",
  "title": {
    "type": "plain_text",
    "text": "Plan your study"
  },
  "close": {
    "type": "plain_text",
    "text": "Close"
  },
  "blocks": [
    {
      "type": "context",
      "elements": [
        {
          "type": "mrkdwn",
          "text": "Select a study, then create documents or upload files."
        }
      ]
    },
    {
      "type": "divider"
    },
    {
      "type": "section",
      "text": {
        "type": "mrkdwn",
        "text": "*📂 Select Study*"
      }
    },
    {
      "type": "actions",
      "block_id": "study_select_block",
      "elements": [
        {
          "type": "static_select",
          "action_id": "study_select",
          "placeholder": {
            "type": "plain_text",
            "text": "Select a study..."
          },
          "options": [
            {
              "text": {
                "type": "plain_text",
                "text": "{{study_1_name}}"
              },
              "value": "{{study_1_id}}"
            },
            {
              "text": {
                "type": "plain_text",
                "text": "{{study_2_name}}"
              },
              "value": "{{study_2_id}}"
            }
          ]
        }
      ]
    },
    {
      "type": "divider"
    },
    {
      "type": "section",
      "text": {
        "type": "mrkdwn",
        "text": "*📝 Create Documents*"
      }
    },
    {
      "type": "section",
      "text": {
        "type": "mrkdwn",
        "text": "*Research brief*\nDefine scope, objectives, and methodology"
      },
      "accessory": {
        "type": "button",
        "text": {
          "type": "plain_text",
          "text": "Create"
        },
        "action_id": "create_research_brief",
        "value": "research_brief"
      }
    },
    {
      "type": "section",
      "text": {
        "type": "mrkdwn",
        "text": "*Stakeholder guide*\nQuestions for PMs, engineers, policy SMEs"
      },
      "accessory": {
        "type": "button",
        "text": {
          "type": "plain_text",
          "text": "Create"
        },
        "action_id": "create_stakeholder_guide",
        "value": "stakeholder_guide"
      }
    },
    {
      "type": "section",
      "text": {
        "type": "mrkdwn",
        "text": "*Research plan*\nTimeline, logistics, and session schedule"
      },
      "accessory": {
        "type": "button",
        "text": {
          "type": "plain_text",
          "text": "Create"
        },
        "action_id": "create_research_plan",
        "value": "research_plan"
      }
    },
    {
      "type": "section",
      "text": {
        "type": "mrkdwn",
        "text": "*Discussion guide*\nConversation guide for user research sessions"
      },
      "accessory": {
        "type": "button",
        "text": {
          "type": "plain_text",
          "text": "Create"
        },
        "action_id": "create_discussion_guide",
        "value": "discussion_guide"
      }
    },
    {
      "type": "divider"
    },
    {
      "type": "section",
      "text": {
        "type": "mrkdwn",
        "text": "*📎 Upload Files*"
      }
    },
    {
      "type": "section",
      "text": {
        "type": "mrkdwn",
        "text": "*Desk research*\nReports, competitive analysis, background docs"
      },
      "accessory": {
        "type": "button",
        "text": {
          "type": "plain_text",
          "text": "Upload"
        },
        "action_id": "upload_desk_research",
        "value": "desk_research"
      }
    },
    {
      "type": "section",
      "text": {
        "type": "mrkdwn",
        "text": "*Stakeholder notes*\nTranscripts from internal interviews"
      },
      "accessory": {
        "type": "button",
        "text": {
          "type": "plain_text",
          "text": "Upload"
        },
        "action_id": "upload_stakeholder_notes",
        "value": "stakeholder_notes"
      }
    },
    {
      "type": "section",
      "text": {
        "type": "mrkdwn",
        "text": "*Survey data*\nSurvey exports (CSV, Excel) for synthesis"
      },
      "accessory": {
        "type": "button",
        "text": {
          "type": "plain_text",
          "text": "Upload"
        },
        "action_id": "upload_survey_data",
        "value": "survey_data"
      }
    },
    {
      "type": "divider"
    },
    {
      "type": "context",
      "elements": [
        {
          "type": "mrkdwn",
          "text": "💡 Upload stakeholder notes to unlock Service Blueprint analysis"
        }
      ]
    }
  ]
}
